{
    "fileName": "TalonLib.json",
    "name": "TalonLib",
    "version": "main-SNAPSHOT",
    "uuid": "69c4e3e3-c33d-4e8c-8985-6a5bac2a6fee",
    "mavenUrls": [
        "https://frcmaven.wpi.edu/artifactory/release",
        "https://maven.ctr-electronics.com/release",
        "https://maven.revrobotics.com",
        "https://repo1.maven.org/maven2"
    ],
    "jsonUrl": "https://raw.githubusercontent.com/Talon540Programming/TalonLib/main/TalonLib.json",
    "jniDependencies": [],
    "cppDependencies": [],
    "javaDependencies": [
        {
            "groupId": "com.ctre.phoenix",
            "artifactId": "api-java",
            "version": "5.21.1"
          },
          {
            "groupId": "com.ctre.phoenix",
            "artifactId": "wpiapi-java",
            "version": "5.21.1"
          },
          {
            "groupId": "com.revrobotics.frc",
            "artifactId": "REVLib-java",
            "version": "2022.1.0"
          },
          {
            "groupId": "com.kauailabs.navx.frc",
            "artifactId": "navx-java",
            "version": "4.0.447"
          }
    ]


}